{"sections":{"page-header-collection":{"type":"page-header--collection","settings":{}},"collection_list_LH9CmH":{"type":"collection-list","blocks":{"collection_BqyDyB":{"type":"collection","settings":{"collection":"fathers-day"}},"collection_UrJzct":{"type":"collection","settings":{"collection":"gifts-under-100-fathers-day"}},"collection_fJYAGk":{"type":"collection","settings":{"collection":"work-wear-selects"}},"collection_Mwhkcf":{"type":"collection","settings":{"collection":"travel"}},"collection_BQ34Nk":{"type":"collection","settings":{"collection":"golf-apparel"}},"collection_kUKpFU":{"type":"collection","settings":{"collection":"off-duty"}},"collection_K8YUE3":{"type":"collection","settings":{"collection":"fathers-day-gift-guide"}}},"block_order":["collection_BqyDyB","collection_UrJzct","collection_fJYAGk","collection_Mwhkcf","collection_BQ34Nk","collection_kUKpFU","collection_K8YUE3"],"settings":{"section_id":"","title":"Shop by Gift Guide"}},"main-collection":{"type":"main-content--collection","settings":{"collection-driver-title":"","collection-driver-text":"","collection-driver-button-text":"","collection-driver-link":"","enable_sorting":true,"enable_filtering":true}}},"order":["page-header-collection","collection_list_LH9CmH","main-collection"]}